recurtx/__init__.py
recurtx/__main__.py
recurtx/ll.py
recurtx/pandas.py
recurtx/polars.py
recurtx/recur.py
recurtx/search.py
recurtx/utils.py
recurtx-0.0.24.dist-info/LICENSE
recurtx-0.0.24.dist-info/METADATA
recurtx-0.0.24.dist-info/WHEEL
recurtx-0.0.24.dist-info/entry_points.txt
recurtx-0.0.24.dist-info/top_level.txt
recurtx-0.0.24.dist-info/RECORD
